mp3toolsce/__init__.py
mp3toolsce/__main__.py
mp3toolsce/mp3tools.py
mp3toolsce-1.0.8.dist-info/LICENSE
mp3toolsce-1.0.8.dist-info/METADATA
mp3toolsce-1.0.8.dist-info/WHEEL
mp3toolsce-1.0.8.dist-info/entry_points.txt
mp3toolsce-1.0.8.dist-info/top_level.txt
mp3toolsce-1.0.8.dist-info/RECORD
