Metadata-Version: 2.1
Name: mp3toolsce
Version: 1.0.8
Summary: Tools for merging mp3 files using foobar2000, e.g. audiobooks
Home-page: https://github.com/carsten-engelke/mp3-tools
Author: Carsten Engelke
Author-email: carsten.engelke@gmail.com
Classifier: Programming Language :: Python :: 3
Classifier: License :: OSI Approved :: MIT License
Classifier: Operating System :: OS Independent
Requires-Python: >=3.6
License-File: LICENSE
Requires-Dist: autopep8 (>=1)
Requires-Dist: natsort (>=7)
Requires-Dist: pycodestyle (>=2)
Requires-Dist: pynput (>=1)
Requires-Dist: six (>=1)
